{
	"configurations" : 
	[
		{
			"directories" : 
			[
				{
					"build" : ".",
					"jsonFile" : "directory-.-Debug-d0094a50bb2071803777.json",
					"minimumCMakeVersion" : 
					{
						"string" : "3.21"
					},
					"projectIndex" : 0,
					"source" : ".",
					"targetIndexes" : 
					[
						0
					]
				}
			],
			"name" : "Debug",
			"projects" : 
			[
				{
					"directoryIndexes" : 
					[
						0
					],
					"name" : "All_labs225",
					"targetIndexes" : 
					[
						0
					]
				}
			],
			"targets" : 
			[
				{
					"directoryIndex" : 0,
					"id" : "All_labs225::@6890427a1f51a3e7e1df",
					"jsonFile" : "target-All_labs225-Debug-cd20426289696027d447.json",
					"name" : "All_labs225",
					"projectIndex" : 0
				}
			]
		}
	],
	"kind" : "codemodel",
	"paths" : 
	{
		"build" : "C:/Users/boray/CLionProjects/All_labs225/cmake-build-debug",
		"source" : "C:/Users/boray/CLionProjects/All_labs225"
	},
	"version" : 
	{
		"major" : 2,
		"minor" : 3
	}
}
